useraudit/__init__.py
useraudit/admin.py
useraudit/backend.py
useraudit/middleware.py
useraudit/models.py
useraudit/password_expiry.py
useraudit/signals.py
useraudit/test_settings.py
useraudit/test_urls.py
useraudit/urls.py
useraudit/views.py
useraudit/migrations/0001_initial.py
useraudit/migrations/0002_loginattempt.py
useraudit/migrations/0003_auto_20160406_1434.py
useraudit/migrations/0004_enlarge_user_agent_field.py
useraudit/migrations/0005_add_userdeactivation_table.py
useraudit/migrations/0006_add_userdeactivation_table_unicode_fixup.py
useraudit/migrations/0007_typo.py
useraudit/migrations/__init__.py
django_useraudit-1.7.1.dist-info/LICENSE
django_useraudit-1.7.1.dist-info/METADATA
django_useraudit-1.7.1.dist-info/WHEEL
django_useraudit-1.7.1.dist-info/top_level.txt
django_useraudit-1.7.1.dist-info/zip-safe
django_useraudit-1.7.1.dist-info/RECORD
